<?xml version="1.0"?>
<law>
  <structure>
    <unit label="title" identifier="c3" order_by="" level="1"/>
    <unit label="chapter" identifier="25" order_by="" level="2"/>
  </structure>
  <section_number>c3-25</section_number>
  <catch_line/>
  <text>Neither House shall, without the consent of the other, adjourn for more than three days, at any one time, nor adjourn to any other place, than that in which the House shall be sitting, without the concurrent vote of two-thirds of the members present.</text>
</law>
