<?xml version="1.0"?>
<law>
  <structure>
    <unit label="article" identifier="gag" order_by="" level="1">Agriculture</unit>
  </structure>
  <section_number>gag-8-904</section_number>
  <catch_line>Nothing in this subtitle is intended to supplant or limit the authority of the Department of the Env...</catch_line>
  <order_by>904</order_by>
  <text>Nothing in this subtitle is intended to supplant or limit the authority of the Department of the Environment to establish eligibility and other requirements for use of nutrient or sediment offset credits under any State or federal permit or other regulatory program.</text>
</law>
