<?xml version="1.0"?>
<law>
  <structure>
    <unit label="article" identifier="gag" order_by="gag" level="1">Agriculture</unit>
  </structure>
  <section_number>gag-5-209</section_number>
  <catch_line>Each commercial application of a pesticide shall be under the supervision of a certified pest contro...</catch_line>
  <order_by>209</order_by>
  <text>Each commercial application of a pesticide shall be under the supervision of a certified pest control applicator or certified public agency applicator who is responsible and liable for the application. Each application of a restricted use pesticide by a certified private applicator shall be done under his supervision, and he is responsible and liable for the application.</text>
</law>
