<?xml version="1.0"?>
<law>
  <structure>
    <unit label="article" identifier="gca" order_by="gca" level="1">Corporations and Associations</unit>
  </structure>
  <section_number>gca-7-204</section_number>
  <catch_line>A corporation which is registered or qualified under this subtitle may obtain a certificate of regis...</catch_line>
  <order_by>204</order_by>
  <text>A corporation which is registered or qualified under this subtitle may obtain a certificate of registration or qualification from the Department. The certificate shall show the address of any principal office in this State which is certified to the Department.</text>
</law>
