<?xml version="1.0"?>
<law>
  <structure>
    <unit label="article" identifier="gcj" order_by="" level="1">Courts and Judicial Proceedings</unit>
  </structure>
  <section_number>gcj-12-308</section_number>
  <catch_line>Except as provided in &#xA7; 12-307 of this subtitle, the Court of Special Appeals has exclusive initial...</catch_line>
  <order_by>308</order_by>
  <text>Except as provided in &#xA7; 12-307 of this subtitle, the Court of Special Appeals has exclusive initial appellate jurisdiction over any reviewable judgment, decree, order or other action of a circuit court, and an orphans' court.</text>
</law>
