<?xml version="1.0"?>
<law>
  <structure>
    <unit label="article" identifier="gcj" order_by="" level="1">Courts and Judicial Proceedings</unit>
  </structure>
  <section_number>gcj-2-211</section_number>
  <catch_line>When the Governor issues a civil commission and the Secretary of State delivers the commission to th...</catch_line>
  <order_by>211</order_by>
  <text>When the Governor issues a civil commission and the Secretary of State delivers the commission to the clerk of a circuit court, the clerk immediately shall deliver the commission to the person to whom the commission is directed and who applies for the commission.</text>
</law>
