<?xml version="1.0"?>
<law>
  <structure>
    <unit label="title" identifier="gcj" order_by="" level="1"/>
    <unit label="chapter" identifier="10-412" order_by="" level="2"/>
  </structure>
  <section_number>gcj-10-412</section_number>
  <catch_line/>
  <text>Any person who breaks and enters, enters under false pretenses, or trespasses, upon any premises with the intent to place, adjust or remove wiretapping or electronic surveillance or eavesdropping equipment without a court order is guilty of a felony and upon conviction may be imprisoned for not more than ten years.</text>
</law>
