<?xml version="1.0"?>
<law>
  <structure>
    <unit label="article" identifier="gcj" order_by="gcj" level="1">Courts and Judicial Proceedings</unit>
  </structure>
  <section_number>gcj-3-503</section_number>
  <catch_line>An owner, licensee, or operator of a television or radio station or network of stations, and his age...</catch_line>
  <order_by>503</order_by>
  <text>An owner, licensee, or operator of a television or radio station or network of stations, and his agents or employees are not liable for a defamatory statement published or uttered over the facilities of the station or network of stations by a candidate for public office as to his opponents for the office he seeks, if the publication or utterance cannot be censored by the owner, licensee, or operator under any regulation of the Federal Communications Commission or a federal statute.</text>
</law>
