<?xml version="1.0"?>
<law>
  <structure>
    <unit label="article" identifier="gcs" order_by="gcs" level="1">Correctional Services</unit>
  </structure>
  <section_number>gcs-4-307</section_number>
  <catch_line>If a court has ordered that an eligible person make restitution as part of a sentence or as a condit...</catch_line>
  <order_by>307</order_by>
  <text>If a court has ordered that an eligible person make restitution as part of a sentence or as a condition of probation, the Board of Review shall require the eligible person to make restitution payments while on parole or work release as a condition of parole or work release.</text>
</law>
