<?xml version="1.0"?>
<law>
  <structure>
    <unit label="title" identifier="gcs" order_by="" level="1"/>
    <unit label="chapter" identifier="9-304" order_by="" level="2"/>
  </structure>
  <section_number>gcs-9-304</section_number>
  <catch_line/>
  <text>By mutual agreement with a county or counties, the Commissioner of Correction may transfer a minimum security inmate to a local correctional facility operated by the county or counties for participation in community-oriented correctional programs.</text>
</law>
