<?xml version="1.0"?>
<law>
  <structure>
    <unit label="article" identifier="gel" order_by="" level="1">Education</unit>
  </structure>
  <section_number>gel-13-336</section_number>
  <catch_line>Subject to &#xA7; 13-337 of this subtitle, the provisions of Part VI and this Part VII of this subtitle ...</catch_line>
  <order_by>336</order_by>
  <text>Subject to &#xA7; 13-337 of this subtitle, the provisions of Part VI and this Part VII of this subtitle and the provisions of this subtitle governing the filing of campaign finance reports are mandatory and not directory.</text>
</law>
