<?xml version="1.0"?>
<law>
  <structure>
    <unit label="article" identifier="gen" order_by="gen" level="1">Environment</unit>
  </structure>
  <section_number>gen-4-311</section_number>
  <catch_line>Any person who has the riparian right to use water in the Severn River Watershed for agricultural pu...</catch_line>
  <order_by>311</order_by>
  <text>Any person who has the riparian right to use water in the Severn River Watershed for agricultural purposes may not lose this right because the State or local government or any of their units condemns the person's land.</text>
</law>
