<?xml version="1.0"?>
<law>
  <structure>
    <unit label="article" identifier="gen" order_by="" level="1">Environment</unit>
  </structure>
  <section_number>gen-15-529</section_number>
  <catch_line>If any provision of this subtitle or the applicability thereof to any person or circumstances is hel...</catch_line>
  <order_by>529</order_by>
  <text>If any provision of this subtitle or the applicability thereof to any person or circumstances is held invalid, the remainder of this subtitle and the application of such provision to other persons or circumstances shall not be affected thereby.</text>
</law>
