<?xml version="1.0"?>
<law>
  <structure>
    <unit label="article" identifier="get" order_by="" level="1">Estates and Trusts</unit>
  </structure>
  <section_number>get-16-112</section_number>
  <catch_line>This title applies to registrations of securities in beneficiary form made before or after October 1...</catch_line>
  <order_by>112</order_by>
  <text>This title applies to registrations of securities in beneficiary form made before or after October 1, 1994, by decedents dying on or after October 1, 1994.</text>
</law>
