<?xml version="1.0"?>
<law>
  <structure>
    <unit label="article" identifier="gfi" order_by="gfi" level="1">Financial Institutions</unit>
  </structure>
  <section_number>gfi-5-204</section_number>
  <catch_line>Instead of making an examination under this subtitle, the Commissioner may accept a copy of the repo...</catch_line>
  <order_by>204</order_by>
  <text>Instead of making an examination under this subtitle, the Commissioner may accept a copy of the report of a reasonably recent examination of the banking institution by a federal banking authority.</text>
</law>
