<?xml version="1.0"?>
<law>
  <structure>
    <unit label="article" identifier="gfl" order_by="gfl" level="1">Family Law</unit>
  </structure>
  <section_number>gfl-5-576</section_number>
  <catch_line>The Department shall issue a license to any applicant who meets the requirements of this Part VII of...</catch_line>
  <order_by>576</order_by>
  <text>The Department shall issue a license to any applicant who meets the requirements of this Part VII of this subtitle and of the rules and regulations adopted under it.</text>
</law>
