<?xml version="1.0"?>
<law>
  <structure>
    <unit label="article" identifier="ghg" order_by="ghg" level="1">Health - General</unit>
  </structure>
  <section_number>ghg-4-302.4</section_number>
  <catch_line>The existence of a health information exchange does not, in itself, create a new cause of action aga...</catch_line>
  <order_by>302.4</order_by>
  <text>The existence of a health information exchange does not, in itself, create a new cause of action against a health information exchange or a health care provider.</text>
</law>
