<?xml version="1.0"?>
<law>
  <structure>
    <unit label="title" identifier="gho" order_by="" level="1"/>
    <unit label="chapter" identifier="14-5B-13" order_by="" level="2"/>
  </structure>
  <section_number>gho-14-5B-13</section_number>
  <catch_line/>
  <text>Unless the Board agrees to accept the surrender of a license or temporary license, a licensee or holder of a temporary license may not surrender the license or temporary license and the license or temporary license may not lapse by operation of law while the licensee or holder of a temporary license is under investigation or while charges are pending against the licensee or holder of a temporary license.</text>
</law>
