<?xml version="1.0"?>
<law>
  <structure>
    <unit label="article" identifier="gin" order_by="" level="1">Insurance</unit>
  </structure>
  <section_number>gin-27-203</section_number>
  <catch_line>A person may not make, publish, disseminate, circulate, place before the public, or cause directly o...</catch_line>
  <order_by>203</order_by>
  <text>A person may not make, publish, disseminate, circulate, place before the public, or cause directly or indirectly to be made, published, disseminated, circulated, or placed before the public in a newspaper, magazine, or other publication, in the form of a notice, circular, pamphlet, letter, or poster, over a radio or television station, or in any other way, an advertisement, announcement, or statement that contains an assertion, representation, or statement about the business of insurance or about a person in the conduct of the person's insurance business that is untrue, deceptive, or misleading.</text>
</law>
