<?xml version="1.0"?>
<law>
  <structure>
    <unit label="article" identifier="gin" order_by="" level="1">Insurance</unit>
  </structure>
  <section_number>gin-14-103</section_number>
  <catch_line>Each nonprofit health service plan shall disclose on each document, statement, announcement, and adv...</catch_line>
  <order_by>103</order_by>
  <text>Each nonprofit health service plan shall disclose on each document, statement, announcement, and advertisement and in any representation it places before the public that the nonprofit health service plan is a private not-for-profit corporation.</text>
</law>
