<?xml version="1.0"?>
<law>
  <structure>
    <unit label="article" identifier="gnr" order_by="gnr" level="1">Natural Resources</unit>
  </structure>
  <section_number>gnr-5-210</section_number>
  <catch_line>The Secretary, upon request, shall assist other State units, counties, towns, corporations, and indi...</catch_line>
  <order_by>210</order_by>
  <text>The Secretary, upon request, shall assist other State units, counties, towns, corporations, and individuals in preparing plans for park, recreation and natural area acquisition and development, acquisition of multiple use areas including protection of watersheds, management, and replacement of trees, woodlots, and timber tracts under an agreement that a party obtaining the assistance, pay at least the field expenses of the men employed in preparing the plans.</text>
</law>
