<?xml version="1.0"?>
<law>
  <structure>
    <unit label="article" identifier="gps" order_by="gps" level="1">Public Safety</unit>
  </structure>
  <section_number>gps-7-213</section_number>
  <catch_line>By resolution or ordinance, the Washington County Commissioners may establish and fund a volunteer l...</catch_line>
  <order_by>213</order_by>
  <text>By resolution or ordinance, the Washington County Commissioners may establish and fund a volunteer length of service award program for qualified members of volunteer fire departments, rescue squads, and ambulance corps.</text>
</law>
