<?xml version="1.0"?>
<law>
  <structure>
    <unit label="article" identifier="gpu" order_by="gpu" level="1">Public Utilities</unit>
  </structure>
  <section_number>gpu-20-103</section_number>
  <catch_line>If the Commission decides to proceed with the design or construction of a water supply or sanitary s...</catch_line>
  <order_by>103</order_by>
  <text>If the Commission decides to proceed with the design or construction of a water supply or sanitary sewer system, the Commission shall comply with the requirements of this subtitle.</text>
</law>
