<?xml version="1.0"?>
<law>
  <structure>
    <unit label="title" identifier="grp" order_by="" level="1"/>
    <unit label="chapter" identifier="8-331" order_by="" level="2"/>
  </structure>
  <section_number>grp-8-331</section_number>
  <catch_line/>
  <text>If the court finds that any notice required under this subtitle to be sent by mail actually has not been received by the person to whom the notice was addressed and that injustice will result, the court shall order a stay of further proceedings until it is satisfied that the person has had an opportunity to protect the person's interests.</text>
</law>
