<?xml version="1.0"?>
<law>
  <structure>
    <unit label="title" identifier="gsg" order_by="" level="1"/>
    <unit label="chapter" identifier="7-219" order_by="" level="2"/>
  </structure>
  <section_number>gsg-7-219</section_number>
  <catch_line/>
  <text>Unless notice by publication is insufficient in law or unless otherwise specifically provided by law, publication of a document under this subtitle gives a person who is subject to or affected by the document notice of the contents of the document.</text>
</law>
