<?xml version="1.0"?>
<law>
  <structure>
    <unit label="article" identifier="gsp" order_by="" level="1">State Personnel and Pensions</unit>
  </structure>
  <section_number>gsp-22-204</section_number>
  <catch_line>If eligibility of an individual for membership in the Employees' Retirement System is unclear, the B...</catch_line>
  <order_by>204</order_by>
  <text>If eligibility of an individual for membership in the Employees' Retirement System is unclear, the Board of Trustees shall determine whether the individual is a member without regard to the method of payment of the individual's compensation.</text>
</law>
