<?xml version="1.0"?>
<law>
  <structure>
    <unit label="article" identifier="gtg" order_by="gtg" level="1">Tax - General</unit>
  </structure>
  <section_number>gtg-10-107</section_number>
  <catch_line>To the extent practicable, the Comptroller shall apply the administrative and judicial interpretatio...</catch_line>
  <order_by>107</order_by>
  <text>To the extent practicable, the Comptroller shall apply the administrative and judicial interpretations of the federal income tax law to the administration of the income tax laws of this State.</text>
</law>
