<?xml version="1.0"?>
<law>
  <structure>
    <unit label="article" identifier="gtp" order_by="" level="1">Tax - Property</unit>
  </structure>
  <section_number>gtp-14-1015</section_number>
  <catch_line>An officer or employee of the State, a county, or municipal corporation who negligently fails to per...</catch_line>
  <order_by>1015</order_by>
  <text>An officer or employee of the State, a county, or municipal corporation who negligently fails to perform a duty or to do any act required in this article is guilty of a misdemeanor and on conviction is subject to a fine not exceeding $1,000.</text>
</law>
