<?xml version="1.0"?>
<law>
  <structure>
    <unit label="article" identifier="gtp" order_by="" level="1">Tax - Property</unit>
  </structure>
  <section_number>gtp-14-840</section_number>
  <catch_line>At the same time the summons is issued as provided by &#xA7; 14-839 of this subtitle, the court shall pa...</catch_line>
  <order_by>840</order_by>
  <text>At the same time the summons is issued as provided by &#xA7; 14-839 of this subtitle, the court shall pass an order of publication directed to all defendants, naming them as provided by this subtitle. The property shall be described in the order of publication as the property is described on the collector's certificate of tax sale. The order of publication shall warn any person that has or claims to have an interest in the property to answer the complaint or to redeem the property on or before the date named in the order of publication and in case of failure to appear, answer, or redeem the property a judgment will be entered that forecloses all rights of redemption in the property. The date named may not be less than 60 days from the date of the order. When the order of publication is issued and published, any person that has any right, title, interest, claim, lien, or equity of redemption in the property is bound by the judgment of the court that may be passed in the case as if the person were personally served with process. The order of publication shall be in substantially the following form:</text>
</law>
